Prototypia/Arf2.py
Prototypia/Arf2Fb.py
Prototypia/Arf2Index.py
Prototypia/WishChild.py
Prototypia/WishGroup.py
Prototypia/__init__.py
Prototypia-0.5.4.dist-info/METADATA
Prototypia-0.5.4.dist-info/WHEEL
Prototypia-0.5.4.dist-info/top_level.txt
Prototypia-0.5.4.dist-info/RECORD
