Metadata-Version: 2.1
Name: Prototypia
Version: 0.5.4
Summary: Aerials Chart[Fumen] Writer & Compiler
Author-email: 1dealGas <i@1deal.cc>
License: MIT License
Keywords: aerials,prototypia,rhythm-game-charting
Classifier: Programming Language :: Python :: 3
Classifier: License :: OSI Approved :: MIT License
Classifier: Operating System :: OS Independent
Requires-Dist: flatbuffers
